serflag/__init__.py
serflag/serflag.py
serflag/serflagmeta.py
serflag-0.0.1.dist-info/LICENSE
serflag-0.0.1.dist-info/METADATA
serflag-0.0.1.dist-info/WHEEL
serflag-0.0.1.dist-info/top_level.txt
serflag-0.0.1.dist-info/RECORD
